iBott-CV/__init__.py
iBott-CV/screen_activities.py
ibott_cv/__init__.py
ibott_cv/screen_activities.py
ibott_cv-1.0.3.dist-info/METADATA
ibott_cv-1.0.3.dist-info/WHEEL
ibott_cv-1.0.3.dist-info/top_level.txt
ibott_cv-1.0.3.dist-info/RECORD
